writer/VERSION.py
writer/VERSION.pyi
writer/__init__.py
writer/__init__.pyi
writer/writer.py
writer/writer.pyi
pywriter_monad-0.3.1.dist-info/WHEEL
pywriter_monad-0.3.1.dist-info/METADATA
pywriter_monad-0.3.1.dist-info/RECORD
