Metadata-Version: 2.1
Name: pywriter-monad
Version: 0.3.1
Summary: 
Author: Yohei Tamura
Author-email: tamuhey@gmail.com
Requires-Python: >=3.6
Classifier: Programming Language :: Python :: 3
Classifier: Programming Language :: Python :: 3.6
Classifier: Programming Language :: Python :: 3.7
Classifier: Programming Language :: Python :: 3.8
Classifier: Programming Language :: Python :: 3.9
Requires-Dist: dataclasses (>=0.6); python_version < "3.7"
Requires-Dist: typing-extensions (>=3.7.4,<4.0.0); python_version < "3.8"
